ALU/alu.sv
module alu (
  input  logic [31:0] operand1,   // Operando 1 (32 bits)
  input  logic [31:0] operand2,   // Operando 2 (32 bits)
  input  logic [2:0]  funct3,     // ← CAMBIAR de func3 a funct3
  input  logic subsra,            // Control extra: SUB/ADD o SRA/SRL
  output logic [31:0] result      // Resultado de la operación
);

  logic signed [31:0] signed_op1;  // Variable auxiliar signed
  
  always_comb begin
    signed_op1 = operand1;  // Conversión a signed
    
    case (funct3)  // ← CAMBIAR aquí también
      3'b000: // ADD o SUB
        result = subsra ? (operand1 - operand2) : (operand1 + operand2);
      
      3'b001: // Shift Left Logical (SLL)
        result = operand1 << operand2[4:0]; // Solo 5 bits para shift en RV32
      
      3'b010: // Set Less Than (signed)
        result = ($signed(operand1) < $signed(operand2)) ? 32'd1 : 32'd0;
      
      3'b011: // Set Less Than Unsigned (SLTU)
        result = (operand1 < operand2) ? 32'd1 : 32'd0;
      
      3'b100: // XOR
        result = operand1 ^ operand2;
      
      3'b101: // Shift Right Logical (SRL) o Shift Right Arithmetic (SRA)
        if (subsra)
          result = signed_op1 >>> operand2[4:0];
        else
          result = operand1 >> operand2[4:0];
      
      3'b110: // OR
        result = operand1 | operand2;
      
      3'b111: // AND
        result = operand1 & operand2;
      
      default: // Por seguridad
        result = 32'd0;
    endcase
  end

endmodule

REGISTER_UNIT/register_unit.sv
module registerUnit (
  input  logic [4:0]  rs1,
  input  logic [4:0]  rs2,
  input  logic [4:0]  rd, 
  input  logic        clk,
  input  logic        writeEnable,
  input  logic [31:0] data,
  input  logic        tr,   // modo "trace"
  
  output logic [31:0] rs1Data,
  output logic [31:0] rs2Data
);

  // Banco de 32 registros de 32 bits
  logic [31:0] registers[31:0];

  // Escritura síncrona
  always_ff @(posedge clk) begin
    if (writeEnable && rd != 5'd0)
      registers[rd] <= data;
    registers[0] <= 32'd0; // x0 siempre en 0
  end

  // Lectura combinacional
  assign rs1Data = registers[rs1];
  assign rs2Data = registers[rs2];

  // Debug (mostrar contenido)
  always_ff @(posedge clk) begin
    if (tr) begin
      for (int i = 0; i < 32; i++) begin
        $display("R[%0d] = %0d", i, registers[i]);
      end
    end
  end

endmodule

QUARTUS_VGA/control_unit.sv
module control_unit (
  input  logic [6:0] opcode,
  input  logic [2:0] funct3,
  input  logic [6:0] funct7,
  
  output logic       ru_write,
  output logic [3:0] alu_op,
  output logic [2:0] imm_src,
  output logic [1:0] alu_a_src,
  output logic       alu_b_src,
  output logic       dm_write,
  output logic [2:0] dm_ctrl,
  output logic [4:0] br_op,
  output logic [1:0] ru_data_src
);

  always_comb begin
    // Valores por defecto
    ru_write     = 1'b0;
    alu_op       = 4'b0000;
    imm_src      = 3'b000;
    alu_a_src    = 2'b00;
    alu_b_src    = 1'b0;
    dm_write     = 1'b0;
    dm_ctrl      = 3'b000;
    br_op        = 5'b00000;
    ru_data_src  = 2'b00;
    
    case (opcode)
      7'b0110011: begin // Tipo R
        ru_write     = 1'b1;
        alu_op       = {funct7[5], funct3};
        imm_src      = 3'bxxx;
        alu_a_src    = 2'b00;
        alu_b_src    = 1'b0;
        dm_write     = 1'b0;
        dm_ctrl      = 3'bxxx;
        br_op        = 5'b00xxx;
        ru_data_src  = 2'b00;
      end
      
      7'b0010011: begin // Tipo I (Operaciones inmediatas)
        ru_write     = 1'b1;
        imm_src      = 3'b000;
        alu_a_src    = 2'b00;
        alu_b_src    = 1'b1;
        dm_write     = 1'b0;
        dm_ctrl      = 3'bxxx;
        br_op        = 5'b00xxx;
        ru_data_src  = 2'b00;
        
        // Diferenciar shifts de otras operaciones
        case (funct3)
          3'b001, 3'b101: // SLLI, SRLI/SRAI (shifts usan funct7[5])
            alu_op = {funct7[5], funct3};
          default: // ADDI, SLTI, SLTIU, XORI, ORI, ANDI (no usan funct7[5])
            alu_op = {1'b0, funct3};
        endcase
      end
      
      7'b0000011: begin // Tipo I (Load)
        ru_write     = 1'b1;
        alu_op       = 4'b0000; // ADD
        imm_src      = 3'b000;
        alu_a_src    = 2'b00;
        alu_b_src    = 1'b1;
        dm_write     = 1'b0;
        dm_ctrl      = funct3;
        br_op        = 5'b00xxx;
        ru_data_src  = 2'b01;
      end
		
		7'b0100011: begin // TIPO S (Store)
		  ru_write     = 1'b0;    // NO escribir en registros
        alu_op       = 4'b0000; // ADD (calcular dirección)
        imm_src      = 3'b001;  // Inmediato tipo S
        alu_a_src    = 2'b00;   // rs1 (registro base)
        alu_b_src    = 1'b1;    // Usar inmediato (offset)
        dm_write     = 1'b1;    // SÍ escribir en memoria
        dm_ctrl      = funct3;  // Control según tipo de store (SB, SH, SW)
        br_op        = 5'b00xxx;
        ru_data_src  = 2'bxx;   // No importa, no escribimos en registros
      end

      7'b0110111: begin // LUI (Load Upper Immediate)
        ru_write     = 1'b1;    // SÍ escribir en rd
        alu_op       = 4'bxxxx; // ALU no se usa
        imm_src      = 3'b100;  // Inmediato tipo U
        alu_a_src    = 2'bxx;   // No importa
        alu_b_src    = 1'bx;    // No importa
        dm_write     = 1'b0;    // NO escribir en memoria
        dm_ctrl      = 3'bxxx;  // No importa
        br_op        = 5'b00xxx;
        ru_data_src  = 2'b11;   // Escribir directamente el inmediato
      end
      
      7'b0010111: begin // AUIPC (Add Upper Immediate to PC)
        ru_write     = 1'b1;    // SÍ escribir en rd
        alu_op       = 4'b0000; // ADD
        imm_src      = 3'b100;  // Inmediato tipo U
        alu_a_src    = 2'b01;   // Usar PC como operando A
        alu_b_src    = 1'b1;    // Usar inmediato como operando B
        dm_write     = 1'b0;    // NO escribir en memoria
        dm_ctrl      = 3'bxxx;  // No importa
        br_op        = 5'b00xxx;
        ru_data_src  = 2'b00;   // Resultado de ALU (PC + imm)
      end		    
      
      default: begin
        ru_write     = 1'b0;
        alu_op       = 4'b0000;
        imm_src      = 3'b000;
        alu_a_src    = 2'b00;
        alu_b_src    = 1'b0;
        dm_write     = 1'b0;
        dm_ctrl      = 3'b000;
        br_op        = 5'b00000;
        ru_data_src  = 2'b00;
      end
    endcase
  end

endmodule

DECODER/instruction_decoder.sv
module instruction_decoder (
  input  logic [31:0] instruction,
  
  output logic [6:0]  opcode,
  output logic [4:0]  rd,
  output logic [2:0]  funct3,
  output logic [4:0]  rs1,
  output logic [4:0]  rs2,
  output logic [6:0]  funct7
);

  // Decodificación según formato RISC-V
  assign opcode = instruction[6:0];
  assign rd     = instruction[11:7];
  assign funct3 = instruction[14:12];
  assign rs1    = instruction[19:15];
  assign rs2    = instruction[24:20];
  assign funct7 = instruction[31:25];

endmodule

IMEM/instruction_memory.sv
module instruction_memory (
  input  logic [31:0] address,
  output logic [31:0] instruction
);
  // Memoria de instrucciones
  logic [31:0] memory [0:255]; // 256 palabras de 32 bits
  
  // Lectura combinacional
  assign instruction = memory[address[31:2]]; // Divide por 4 (word-aligned)
  
  // Inicialización (puedes cargar desde archivo)
  initial begin
    // Ejemplo de instrucciones tipo R
    // ADD x1, x2, x3: 0x003100B3
    memory[0] = 32'h003100B3;
    // Inicializa el resto en 0
    for (int i = 1; i < 256; i++) 
      memory[i] = 32'h00000000;
  end
endmodule

QUARTUS/sumador.sv
module sumador (
  input wire[31:0] input_1,
  output wire[31:0] output_32
);

  assign output_32 = input_1 + 4;

endmodule

QUARTUS/pc.sv
module pc (
  input[31:0] next_address,
  input clk,
  input reset,
  input[31:0] initial_address,

  output reg[31:0] address
);

  always @(posedge clk) begin
    if (reset)
      address <= initial_address;
    else 
      address <= next_address;
  end
  
endmodule

MONOCYCLE/monocycle.sv
// NO incluir archivos aquí - iverilog los compila todos juntos

module monocycle (
  input  logic        clk,
  input  logic        reset,
  input  logic [31:0] initial_pc,
  input  logic        tr,          // trace mode
  
  output logic [31:0] pc_out,
  output logic [31:0] instruction_out
);

  // Señales internas
  logic [31:0] pc_current;
  logic [31:0] pc_next;
  logic [31:0] instruction;
  
  // Señales del decoder
  logic [6:0]  opcode;
  logic [4:0]  rd, rs1, rs2;
  logic [2:0]  funct3;
  logic [6:0]  funct7;
  
  // Señales de control completas
  logic        ru_write;
  logic [3:0]  alu_op;
  logic [2:0]  imm_src;
  logic [1:0]  alu_a_src;
  logic        alu_b_src;
  logic        dm_write;
  logic [2:0]  dm_ctrl;
  logic [4:0]  br_op;
  logic [1:0]  ru_data_src;
  
  // Señales de datos
  logic [31:0] rs1Data, rs2Data;
  logic [31:0] aluResult;
  logic        subsra;  // Extraído de alu_op
  
  // Extracción de subsra desde alu_op[3]
  assign subsra = alu_op[3];
  
  // Salidas
  assign pc_out = pc_current;
  assign instruction_out = instruction;
  
  // ========== INSTANCIAS DE MÓDULOS ==========
  
  // Program Counter
  pc program_counter (
    .next_address(pc_next),
    .clk(clk),
    .reset(reset),
    .initial_address(initial_pc),
    .address(pc_current)
  );
  
  // Sumador PC + 4
  sumador pc_adder (
    .input_1(pc_current),
    .output_32(pc_next)
  );
  
  // Instruction Memory
  instruction_memory imem (
    .address(pc_current),
    .instruction(instruction)
  );
  
  // Instruction Decoder
  instruction_decoder decoder (
    .instruction(instruction),
    .opcode(opcode),
    .rd(rd),
    .funct3(funct3),
    .rs1(rs1),
    .rs2(rs2),
    .funct7(funct7)
  );
  
  // Control Unit (Completa para tipo R)
  control_unit control (
    .opcode(opcode),
    .funct3(funct3),
    .funct7(funct7),
    .ru_write(ru_write),
    .alu_op(alu_op),
    .imm_src(imm_src),
    .alu_a_src(alu_a_src),
    .alu_b_src(alu_b_src),
    .dm_write(dm_write),
    .dm_ctrl(dm_ctrl),
    .br_op(br_op),
    .ru_data_src(ru_data_src)
  );
  
  // Register Unit
  registerUnit reg_file (
    .rs1(rs1),
    .rs2(rs2),
    .rd(rd),
    .clk(clk),
    .writeEnable(ru_write),
    .data(aluResult),
    .tr(tr),
    .rs1Data(rs1Data),
    .rs2Data(rs2Data)
  );
  
  // ALU
  alu arithmetic_logic_unit (
    .operand1(rs1Data),
    .operand2(rs2Data),
    .funct3(funct3),
    .subsra(subsra),
    .result(aluResult)
  );

endmodule

MONOCYCLE/tb_monocycle.sv
`timescale 1ns/1ps

module tb_monocycle;

  // Señales del testbench
  logic        clk;
  logic        reset;
  logic [31:0] initial_pc;
  logic        tr;
  logic [31:0] pc_out;
  logic [31:0] instruction_out;
  
  // Instancia del DUT (Device Under Test)
  monocycle dut (
    .clk(clk),
    .reset(reset),
    .initial_pc(initial_pc),
    .tr(tr),
    .pc_out(pc_out),
    .instruction_out(instruction_out)
  );
  
  // Generador de reloj (periodo de 10ns = 100MHz)
  initial begin
    clk = 0;
    forever #5 clk = ~clk;
  end
  
  // Variables para control
  int cycle_count = 0;
  
  // Contador de ciclos
  always @(posedge clk) begin
    if (!reset) begin
      cycle_count++;
    end
  end
  
  // Proceso de prueba
  initial begin
    $display("========================================");
    $display("   TESTBENCH MONOCICLO - TIPO R");
    $display("========================================\n");
    
    // Inicialización
    reset = 1;
    initial_pc = 32'h00000000;
    tr = 0;  // Desactivar trace inicialmente
    
    // Aplicar reset
    #15;
    reset = 0;
    $display("Reset liberado en t=%0t", $time);
    $display("PC inicial: 0x%08h\n", pc_out);
    
    // Ejecutar 15 ciclos (12 instrucciones + margen)
    repeat(15) begin
      @(posedge clk);
      #1; // Pequeño delay para estabilizar señales
      
      $display("----------------------------------------");
      $display("Ciclo %0d | Tiempo: %0t", cycle_count, $time);
      $display("PC: 0x%08h", pc_out);
      $display("Instrucción: 0x%08h", instruction_out);
      
      // Decodificar y mostrar la instrucción
      decode_and_display(instruction_out);
      
      $display("");
    end
    
    // Mostrar estado final de los registros
    $display("\n========================================");
    $display("   ESTADO FINAL DE REGISTROS");
    $display("========================================");
    tr = 1; // Activar trace para mostrar registros
    @(posedge clk);
    #1;
    tr = 0;
    
    $display("\n========================================");
    $display("   SIMULACIÓN COMPLETADA");
    $display("========================================");
    $display("Total de ciclos ejecutados: %0d", cycle_count);
    $display("Tiempo total: %0t", $time);
    
    #20;
    $finish;
  end
  
  // Task para decodificar y mostrar instrucciones
  task decode_and_display(input logic [31:0] instr);
    logic [6:0] opcode;
    logic [4:0] rd, rs1, rs2;
    logic [2:0] funct3;
    logic [6:0] funct7;
    string operation;
    
    opcode = instr[6:0];
    rd     = instr[11:7];
    funct3 = instr[14:12];
    rs1    = instr[19:15];
    rs2    = instr[24:20];
    funct7 = instr[31:25];
    
    if (opcode == 7'b0110011) begin
      // Tipo R
      case ({funct7[5], funct3})
        4'b0000: operation = "ADD";
        4'b1000: operation = "SUB";
        4'b0001: operation = "SLL";
        4'b0010: operation = "SLT";
        4'b0011: operation = "SLTU";
        4'b0100: operation = "XOR";
        4'b0101: operation = "SRL";
        4'b1101: operation = "SRA";
        4'b0110: operation = "OR";
        4'b0111: operation = "AND";
        default: operation = "UNKNOWN";
      endcase
      
      $display("Tipo: R");
      $display("Operación: %s x%0d, x%0d, x%0d", operation, rd, rs1, rs2);
      $display("  opcode=0x%02h, rd=%0d, func3=0x%01h, rs1=%0d, rs2=%0d, func7=0x%02h",
               opcode, rd, funct3, rs1, rs2, funct7);
    end else begin
      $display("Tipo: NO TIPO R (opcode=0x%02h)", opcode);
    end
  endtask
  
  // Monitor de señales críticas
  initial begin
    $monitor("T=%0t | PC=0x%08h | Instr=0x%08h", 
             $time, pc_out, instruction_out);
  end
  
  // Generación de archivo VCD para GTKWave (opcional)
  initial begin
    $dumpfile("tb_monocycle.vcd");
    $dumpvars(0, tb_monocycle);
  end

endmodule

tb_monocycle.vcd
$date
	Fri Oct 03 17:30:06 2025
$end
$version
	Icarus Verilog
$end
$timescale
	1ps
$end
$scope module tb_monocycle $end
$var wire 32 ! pc_out [31:0] $end
$var wire 32 " instruction_out [31:0] $end
$var reg 1 # clk $end
$var reg 32 $ initial_pc [31:0] $end
$var reg 1 % reset $end
$var reg 1 & tr $end
$var integer 32 ' cycle_count [31:0] $end
$scope module dut $end
$var wire 1 # clk $end
$var wire 32 ( initial_pc [31:0] $end
$var wire 32 ) instruction_out [31:0] $end
$var wire 32 * pc_out [31:0] $end
$var wire 1 % reset $end
$var wire 1 & tr $end
$var wire 1 + subsra $end
$var wire 1 , ru_write $end
$var wire 2 - ru_data_src [1:0] $end
$var wire 32 . rs2Data [31:0] $end
$var wire 5 / rs2 [4:0] $end
$var wire 32 0 rs1Data [31:0] $end
$var wire 5 1 rs1 [4:0] $end
$var wire 5 2 rd [4:0] $end
$var wire 32 3 pc_next [31:0] $end
$var wire 32 4 pc_current [31:0] $end
$var wire 7 5 opcode [6:0] $end
$var wire 32 6 instruction [31:0] $end
$var wire 3 7 imm_src [2:0] $end
$var wire 7 8 funct7 [6:0] $end
$var wire 3 9 funct3 [2:0] $end
$var wire 1 : dm_write $end
$var wire 3 ; dm_ctrl [2:0] $end
$var wire 5 < br_op [4:0] $end
$var wire 4 = alu_op [3:0] $end
$var wire 1 > alu_b_src $end
$var wire 2 ? alu_a_src [1:0] $end
$var wire 32 @ aluResult [31:0] $end
$scope module arithmetic_logic_unit $end
$var wire 1 + subsra $end
$var wire 32 A operand2 [31:0] $end
$var wire 32 B operand1 [31:0] $end
$var wire 3 C funct3 [2:0] $end
$var reg 32 D result [31:0] $end
$var reg 32 E signed_op1 [31:0] $end
$upscope $end
$scope module control $end
$var wire 7 F opcode [6:0] $end
$var wire 7 G funct7 [6:0] $end
$var wire 3 H funct3 [2:0] $end
$var reg 2 I alu_a_src [1:0] $end
$var reg 1 > alu_b_src $end
$var reg 4 J alu_op [3:0] $end
$var reg 5 K br_op [4:0] $end
$var reg 3 L dm_ctrl [2:0] $end
$var reg 1 : dm_write $end
$var reg 3 M imm_src [2:0] $end
$var reg 2 N ru_data_src [1:0] $end
$var reg 1 , ru_write $end
$upscope $end
$scope module decoder $end
$var wire 5 O rs2 [4:0] $end
$var wire 5 P rs1 [4:0] $end
$var wire 5 Q rd [4:0] $end
$var wire 7 R opcode [6:0] $end
$var wire 32 S instruction [31:0] $end
$var wire 7 T funct7 [6:0] $end
$var wire 3 U funct3 [2:0] $end
$upscope $end
$scope module imem $end
$var wire 32 V instruction [31:0] $end
$var wire 32 W address [31:0] $end
$upscope $end
$scope module pc_adder $end
$var wire 32 X output_32 [31:0] $end
$var wire 32 Y input_1 [31:0] $end
$upscope $end
$scope module program_counter $end
$var wire 1 # clk $end
$var wire 32 Z initial_address [31:0] $end
$var wire 32 [ next_address [31:0] $end
$var wire 1 % reset $end
$var reg 32 \ address [31:0] $end
$upscope $end
$scope module reg_file $end
$var wire 1 # clk $end
$var wire 32 ] data [31:0] $end
$var wire 5 ^ rd [4:0] $end
$var wire 5 _ rs1 [4:0] $end
$var wire 32 ` rs1Data [31:0] $end
$var wire 5 a rs2 [4:0] $end
$var wire 32 b rs2Data [31:0] $end
$var wire 1 & tr $end
$var wire 1 , writeEnable $end
$scope begin $ivl_for_loop0 $end
$var integer 32 c i [31:0] $end
$upscope $end
$upscope $end
$upscope $end
$scope task decode_and_display $end
$var reg 3 d funct3 [2:0] $end
$var reg 7 e funct7 [6:0] $end
$var reg 32 f instr [31:0] $end
$var reg 7 g opcode [6:0] $end
$var reg 5 h rd [4:0] $end
$var reg 5 i rs1 [4:0] $end
$var reg 5 j rs2 [4:0] $end
$upscope $end
$upscope $end
$enddefinitions $end
$comment Show the parameter values. $end
$dumpall
$end
#0
$dumpvars
bx j
bx i
bx h
bx g
bx f
bx e
bx d
b0 c
bx b
bx a
bx `
bx _
bx ^
b0 ]
bx \
bx [
b0 Z
bx Y
bx X
bx W
bx V
bx U
bx T
bx S
bx R
bx Q
bx P
bx O
b0 N
b0 M
b0 L
b0 K
b0 J
b0 I
bx H
bx G
bx F
bx E
b0 D
bx C
bx B
bx A
b0 @
b0 ?
0>
b0 =
b0 <
b0 ;
0:
bx 9
bx 8
b0 7
bx 6
bx 5
bx 4
bx 3
bx 2
bx 1
bx 0
bx /
bx .
b0 -
0,
0+
bx *
bx )
b0 (
b0 '
0&
1%
b0 $
0#
bx "
bx !
$end
#5000
b100 3
b100 X
b100 [
b0 !
b0 *
b0 4
b0 W
b0 Y
b0 \
1#
#10000
0#
#15000
b1000 3
b1000 X
b1000 [
b100 !
b100 *
b100 4
b100 W
b100 Y
b100 \
b1 '
1#
0%
#20000
0#
#25000
b1100 3
b1100 X
b1100 [
b1000 !
b1000 *
b1000 4
b1000 W
b1000 Y
b1000 \
b10 '
1#
#30000
0#
#35000
b10000 3
b10000 X
b10000 [
b1100 !
b1100 *
b1100 4
b1100 W
b1100 Y
b1100 \
b11 '
1#
#40000
0#
#45000
b10100 3
b10100 X
b10100 [
b10000 !
b10000 *
b10000 4
b10000 W
b10000 Y
b10000 \
b100 '
1#
#50000
0#
#55000
b11000 3
b11000 X
b11000 [
b10100 !
b10100 *
b10100 4
b10100 W
b10100 Y
b10100 \
b101 '
1#
#60000
0#
#65000
b11100 3
b11100 X
b11100 [
b11000 !
b11000 *
b11000 4
b11000 W
b11000 Y
b11000 \
b110 '
1#
#70000
0#
#75000
b100000 3
b100000 X
b100000 [
b11100 !
b11100 *
b11100 4
b11100 W
b11100 Y
b11100 \
b111 '
1#
#80000
0#
#85000
b100100 3
b100100 X
b100100 [
b100000 !
b100000 *
b100000 4
b100000 W
b100000 Y
b100000 \
b1000 '
1#
#90000
0#
#95000
b101000 3
b101000 X
b101000 [
b100100 !
b100100 *
b100100 4
b100100 W
b100100 Y
b100100 \
b1001 '
1#
#100000
0#
#105000
b101100 3
b101100 X
b101100 [
b101000 !
b101000 *
b101000 4
b101000 W
b101000 Y
b101000 \
b1010 '
1#
#110000
0#
#115000
b110000 3
b110000 X
b110000 [
b101100 !
b101100 *
b101100 4
b101100 W
b101100 Y
b101100 \
b1011 '
1#
#120000
0#
#125000
b110100 3
b110100 X
b110100 [
b110000 !
b110000 *
b110000 4
b110000 W
b110000 Y
b110000 \
b1100 '
1#
#130000
0#
#135000
b111000 3
b111000 X
b111000 [
b110100 !
b110100 *
b110100 4
b110100 W
b110100 Y
b110100 \
b1101 '
1#
#140000
0#
#145000
b111100 3
b111100 X
b111100 [
b111000 !
b111000 *
b111000 4
b111000 W
b111000 Y
b111000 \
b1110 '
1#
#150000
0#
#155000
b1000000 3
b1000000 X
b1000000 [
b111100 !
b111100 *
b111100 4
b111100 W
b111100 Y
b111100 \
b1111 '
1#
#156000
1&
#160000
0#
#165000
b1000100 3
b1000100 X
b1000100 [
b1000000 !
b1000000 *
b1000000 4
b1000000 W
b1000000 Y
b1000000 \
b100000 c
b10000 '
1#
#166000
0&
#170000
0#
#175000
b1001000 3
b1001000 X
b1001000 [
b1000100 !
b1000100 *
b1000100 4
b1000100 W
b1000100 Y
b1000100 \
b10001 '
1#
#180000
0#
#185000
b1001100 3
b1001100 X
b1001100 [
b1001000 !
b1001000 *
b1001000 4
b1001000 W
b1001000 Y
b1001000 \
b10010 '
1#
